expurgator.py
expurgator-0.1.3.dist-info/METADATA
expurgator-0.1.3.dist-info/RECORD
expurgator-0.1.3.dist-info/WHEEL
expurgator-0.1.3.dist-info/top_level.txt
