Metadata-Version: 2.1
Name: expurgator
Version: 0.1.3
Summary: Censor sensitive string data in Python.
Home-page: https://github.com/Iress/expurgator
Author: Jeremy Epstein
Author-email: jeremy.epstein@iress.com.au
License: UNKNOWN
Platform: any
Classifier: Development Status :: 2 - Pre-Alpha
Classifier: Environment :: Web Environment
Classifier: Intended Audience :: Developers
Classifier: Operating System :: OS Independent
Classifier: Programming Language :: Python
Classifier: Programming Language :: Python :: 2
Classifier: Programming Language :: Python :: 2.7
Classifier: Programming Language :: Python :: 3
Classifier: Programming Language :: Python :: 3.5
Provides-Extra: dev
Requires-Dist: six
Provides-Extra: dev
Requires-Dist: pytest (>=3); extra == 'dev'
Requires-Dist: coverage; extra == 'dev'
Requires-Dist: coveralls; extra == 'dev'
Requires-Dist: setuptools (>=38.6); extra == 'dev'
Requires-Dist: wheel; extra == 'dev'
